fortune_client/__init__.py
fortune_client/app.py
fortune_client/arguments.py
fortune_client/fortune_api_data.py
fortune_client/fortune_client.py
fortune_client/get_data.py
fortune_client/output.py
fortune_client/parameters.py
fortune_client-0.1.0.dist-info/METADATA
fortune_client-0.1.0.dist-info/WHEEL
fortune_client-0.1.0.dist-info/entry_points.txt
fortune_client-0.1.0.dist-info/RECORD
