Metadata-Version: 2.1
Name: fortune-client
Version: 0.1.0
Summary: 
Author: Łukasz Bacik
Author-email: mail@luka.sh
Requires-Python: >=3.11,<4.0
Classifier: Programming Language :: Python :: 3
Classifier: Programming Language :: Python :: 3.11
Requires-Dist: pydantic (>=2.4.2,<3.0.0)
Requires-Dist: requests (>=2.31.0,<3.0.0)
Requires-Dist: simple-value-object (>=2.0,<3.0)
